week05/cpu.v
module CPU(ck, rst, ia, id, da, dd, rw);
  input ck, rst;
  input [15:0] id;
  output rw;
  output [15:0] ia, da;
  inout [15:0] dd;

  reg [1:0] stage;
  reg [15:0] inst, pc, pcc, fua, fub, lsua, lsub, lsuc, pci, fuc;
  reg [15:0] rf[0:14];
  reg flag, rw;
  wire [15:0] abus, bbus, cbus;
  wire [3:0] opcode, opr1, opr2, opr3;
  wire [7:0] imm;

  assign ia = pc;
  assign opcode = inst[15:12];
  assign opr1 = inst[11:8];
  assign opr2 = inst[7:4];
  assign opr3 = inst[3:0];
  assign imm = inst[7:0];
  assign abus = (opr2 == 0 ? 0 : rf[opr2]);
  assign bbus = (opr3 == 0 ? 0 : rf[opr3]);
  assign da = lsub;
  assign ia = pc;
  assign dd = (rw == 0 ? lsua : 16'b z);
  assign cbus = (opcode[3] == 0 ? fuc
                  : (opcode[3:1] == 'b 101 ? lsuc
                  : (opcode == 'b 1100 ? {8'b 0, imm}
                  : (opcode == 'b 1000 ? pcc : 'b z))));

  always @(posedge ck) begin
    if (rst == 1) begin
      pc <= 0;
      stage <= 0;
      rw <= 1;
    end
    else begin
      if (stage == 0) begin
        inst <= id;
        stage <= 1;
      end
      else if (stage == 1) begin
        if (opcode[3:0] == 'b1000 || (opcode[3:0] == 'b1001 && flag == 1)) begin
          pci <= bbus;
        end
        else begin
          pci <= pc + 1;
        end
        if (opcode[3] == 0) begin
          fua <= abus;
          fub <= bbus;
        end
        else if (opcode[2:1] == 'b01) begin
          lsua <= abus;
          lsub <= bbus;
        end
        stage <= 2;
      end
      else if (stage == 2) begin
        if (opcode[3] == 0) begin
          case (opcode[2:0])
            'b 000: fuc <= fua + fub;
            'b 001: fuc <= fua - fub;
            'b 010: fuc <= fua >> fub;
            'b 011: fuc <= fua << fub;
            'b 100: fuc <= fua | fub;
            'b 101: fuc <= fua & fub;
            'b 110: fuc <= ~fua;
            'b 111: fuc <= fua ^ fub;
          endcase
        end
        if (opcode[3:1] == 'b 101) begin
          if (opcode[0] == 0) begin
            rw <= 0;
          end
          else begin
            rw <= 1;
            lsuc <= dd;
          end
        end
        if (opcode[3:0] == 'b 1000) begin
          pcc <= pc + 1;
        end
        stage <= 3;
      end
      else if (stage == 3) begin
        rw <= 1;
        if (opcode[3] == 0) begin
          if (cbus == 0) flag <= 1;
          else flag <= 0;
        end
        rf[opr1] <= cbus;
        pc <= pci;
        stage <= 0;
      end
    end
  end
endmodule

week05/simcpu4.v
module simcpu;
reg CK, RST;
wire RW;
wire [15:0] IA, DA, DD;
reg [15:0] ID, DDi;
reg [15:0] IMEM [0:127], DMEM[0:127];

wire  [15:0]  DMEM00, DMEM01, DMEM02;
	CPU c(CK,RST,IA,ID,DA,DD,RW);

assign DMEM00 = DMEM[0];
assign DMEM01 = DMEM[1];
assign DMEM02 = DMEM[2];

   assign DD = ((RW == 1) ? DDi : 'b Z);

initial begin
	CK = 0;
	RST = 0;
#5	RST = 1;
#100	RST = 0;
	
        #10000 $finish;
end

always @(negedge CK) begin
   $display( "IA=%h ID=%h DA=%h DD=%h RW=%b, DMEM[2]=%d", IA, ID, DA, DD, RW, DMEM[2]);
   if( DA == 'b 0 && DD == 'b 0100 && RW == 0 ) begin
      $display( "OK" );
      $finish;
   end
end

always @(negedge CK) begin
	ID = IMEM[IA];
end

always @(negedge CK) begin
   if( RW == 1 ) DDi = DMEM[DA];
   else DMEM[DA] = DD;
end

initial begin
DMEM[0]= 5;
DMEM[1]= 15;
//
IMEM[0]='b 1100_0001_0000_0000; // IMM  R1, [0]
IMEM[1]='b 1100_0111_0000_0000; // IMM  R7, [0]
IMEM[2]='b 1100_1000_0000_0001; // IMM  R8, [1]
IMEM[3]='b 1100_1001_0000_0010; // IMM  R9, [2]
IMEM[4]='b 1100_0011_0000_0001; // IMM  R3, [1]
IMEM[5]='b 1100_0101_0000_1101; // IMM  R5, [13]
IMEM[6]='b 1100_0110_0000_1001; // IMM  R6, [9]
IMEM[7]='b 1011_0010_0000_0111; // LD R2, R7
IMEM[8]='b 1011_0100_0000_1000; // LD R4, R8
IMEM[9]='b 0000_0001_0001_0010; // ADD  R1, R1, R2
IMEM[10]='b 0001_0100_0100_0011; // SUB  R4, R4, R3
IMEM[11]='b 1001_0000_0000_0101; // BR f=0, R5
IMEM[12]='b 1000_0000_0000_0110; // JMP R0, R6
IMEM[13]='b 1010_0000_0001_1001; // ST R1, R9
end

always #10 CK = ~CK;

endmodule

week05/cpu.vcd
$date
	Wed May 15 11:28:53 2024
$end
$version
	Icarus Verilog
$end
$timescale
	1s
$end
$scope module simcpu $end
$var wire 16 ! DD [15:0] $end
$var wire 16 " DMEM00 [15:0] $end
$var wire 16 # DMEM01 [15:0] $end
$var wire 16 $ DMEM02 [15:0] $end
$var wire 16 % IA [15:0] $end
$var wire 1 & RW $end
$var wire 16 ' DA [15:0] $end
$var reg 1 ( CK $end
$var reg 16 ) DDi [15:0] $end
$var reg 16 * ID [15:0] $end
$var reg 1 + RST $end
$scope module c $end
$var wire 1 ( ck $end
$var wire 16 , da [15:0] $end
$var wire 16 - dd [15:0] $end
$var wire 16 . ia [15:0] $end
$var wire 16 / id [15:0] $end
$var wire 1 + rst $end
$var wire 4 0 opr3 [3:0] $end
$var wire 4 1 opr2 [3:0] $end
$var wire 4 2 opr1 [3:0] $end
$var wire 4 3 opcode [3:0] $end
$var wire 8 4 imm [7:0] $end
$var wire 16 5 cbus [15:0] $end
$var wire 16 6 bbus [15:0] $end
$var wire 16 7 abus [15:0] $end
$var reg 1 8 flag $end
$var reg 16 9 fua [15:0] $end
$var reg 16 : fub [15:0] $end
$var reg 16 ; fuc [15:0] $end
$var reg 16 < inst [15:0] $end
$var reg 16 = lsua [15:0] $end
$var reg 16 > lsub [15:0] $end
$var reg 16 ? lsuc [15:0] $end
$var reg 16 @ pc [15:0] $end
$var reg 16 A pcc [15:0] $end
$var reg 16 B pci [15:0] $end
$var reg 1 & rw $end
$var reg 2 C stage [1:0] $end
$upscope $end
$upscope $end
$enddefinitions $end
#0
$dumpvars
bx C
bx B
bx A
bx @
bx ?
bx >
bx =
bx <
bx ;
bx :
bx 9
x8
bx 7
bx 6
bx 5
bx 4
bx 3
bx 2
bx 1
bx 0
bx /
bx .
bx -
bx ,
0+
bx *
bx )
0(
bx '
x&
bx %
bx $
bx #
bx "
bx !
$end
#5
1+
#10
1&
b0 C
b0 %
b0 .
b0 @
1(
#20
b1100000100000000 *
b1100000100000000 /
0(
#30
1(
#40
0(
#50
1(
#60
0(
#70
1(
#80
0(
#90
1(
#100
0(
#105
0+
#110
b0 5
b0 7
b0 6
b1100 3
b1 2
b0 1
b0 0
b0 4
b1 C
b1100000100000000 <
1(
#120
0(
#130
b10 C
b1 B
1(
#140
0(
#150
b11 C
1(
#160
0(
#170
b0 C
b1 %
b1 .
b1 @
1(
#180
b1100011100000000 *
b1100011100000000 /
0(
#190
b111 2
b1 C
b1100011100000000 <
1(
#200
0(
#210
b10 C
b10 B
1(
#220
0(
#230
b11 C
1(
#240
0(
#250
b0 C
b10 %
b10 .
b10 @
1(
#260
b1100100000000001 *
b1100100000000001 /
0(
#270
b1 5
b1000 2
b1 0
b1 4
b1 C
b1100100000000001 <
1(
#280
0(
#290
b10 C
b11 B
1(
#300
0(
#310
b11 C
1(
#320
0(
#330
b0 C
b11 %
b11 .
b11 @
1(
#340
b1100100100000010 *
b1100100100000010 /
0(
#350
b10 5
bx 6
b1001 2
b10 0
b10 4
b1 C
b1100100100000010 <
1(
#360
0(
#370
b10 C
b100 B
1(
#380
0(
#390
b11 C
1(
#400
0(
#410
b0 C
b100 %
b100 .
b100 @
1(
#420
b1100001100000001 *
b1100001100000001 /
0(
#430
b1 5
b0 6
b11 2
b1 0
b1 4
b1 C
b1100001100000001 <
1(
#440
0(
#450
b10 C
b101 B
1(
#460
0(
#470
b11 C
1(
#480
0(
#490
b0 C
b101 %
b101 .
b101 @
1(
#500
b1100010100001101 *
b1100010100001101 /
0(
#510
b1101 5
bx 6
b101 2
b1101 0
b1101 4
b1 C
b1100010100001101 <
1(
#520
0(
#530
b10 C
b110 B
1(
#540
0(
#550
b11 C
1(
#560
0(
#570
b0 C
b110 %
b110 .
b110 @
1(
#580
b1100011000001001 *
b1100011000001001 /
0(
#590
b1001 5
b10 6
b110 2
b1001 0
b1001 4
b1 C
b1100011000001001 <
1(
#600
0(
#610
b10 C
b111 B
1(
#620
0(
#630
b11 C
1(
#640
0(
#650
b0 C
b111 %
b111 .
b111 @
1(
#660
b1011001000000111 *
b1011001000000111 /
0(
#670
bx 5
b0 6
b1011 3
b10 2
b111 0
b111 4
b1 C
b1011001000000111 <
1(
#680
0(
#690
b10 C
b0 '
b0 ,
b0 >
b0 =
b1000 B
1(
#700
0(
#710
b11 C
1(
#720
0(
#730
b0 C
b1000 %
b1000 .
b1000 @
1(
#740
b1011010000001000 *
b1011010000001000 /
0(
#750
b1 6
b100 2
b1000 0
b1000 4
b1 C
b1011010000001000 <
1(
#760
0(
#770
b10 C
b1 '
b1 ,
b1 >
b1001 B
1(
#780
0(
#790
b11 C
1(
#800
0(
#810
b0 C
b1001 %
b1001 .
b1001 @
1(
#820
b100010010 *
b100010010 /
0(
#830
bx 6
b0 3
b1 2
b1 1
b10 0
b10010 4
b1 C
b100010010 <
1(
#840
0(
#850
b10 C
b0 9
b1010 B
1(
#860
0(
#870
b11 C
1(
#880
0(
#890
bx 7
b0 C
b1010 %
b1010 .
b1010 @
08
1(
#900
b1010001000011 *
b1010001000011 /
0(
#910
b1 6
b1 3
b100 2
b100 1
b11 0
b1000011 4
b1 C
b1010001000011 <
1(
#920
0(
#930
b10 C
b1 :
bx 9
b1011 B
1(
#940
0(
#950
b11 C
1(
#960
0(
#970
b0 C
b1011 %
b1011 .
b1011 @
1(
#980
b1001000000000101 *
b1001000000000101 /
0(
#990
bz 5
b0 7
b1101 6
b1001 3
b0 2
b0 1
b101 0
b101 4
b1 C
b1001000000000101 <
1(
#1000
0(
#1010
b10 C
b1100 B
1(
#1020
0(
#1030
b11 C
1(
#1040
0(
#1050
b0 C
b1100 %
b1100 .
b1100 @
1(
#1060
b1000000000000110 *
b1000000000000110 /
0(
#1070
bx 5
b1001 6
b1000 3
b110 0
b110 4
b1 C
b1000000000000110 <
1(
#1080
0(
#1090
b10 C
b1001 B
1(
#1100
0(
#1110
b1101 5
b11 C
b1101 A
1(
#1120
0(
#1130
b0 C
b1001 %
b1001 .
b1001 @
1(
#1140
b100010010 *
b100010010 /
0(
#1150
bx 5
bx 7
bx 6
b0 3
b1 2
b1 1
b10 0
b10010 4
b1 C
b100010010 <
1(
#1160
0(
#1170
b10 C
bx :
b1010 B
1(
#1180
0(
#1190
b11 C
1(
#1200
0(
#1210
b0 C
b1010 %
b1010 .
b1010 @
1(
#1220
b1010001000011 *
b1010001000011 /
0(
#1230
b1 6
b1 3
b100 2
b100 1
b11 0
b1000011 4
b1 C
b1010001000011 <
1(
#1240
0(
#1250
b10 C
b1 :
b1011 B
1(
#1260
0(
#1270
b11 C
1(
#1280
0(
#1290
b0 C
b1011 %
b1011 .
b1011 @
1(
#1300
b1001000000000101 *
b1001000000000101 /
0(
#1310
bz 5
b0 7
b1101 6
b1001 3
b0 2
b0 1
b101 0
b101 4
b1 C
b1001000000000101 <
1(
#1320
0(
#1330
b10 C
b1100 B
1(
#1340
0(
#1350
b11 C
1(
#1360
0(
#1370
b0 C
b1100 %
b1100 .
b1100 @
1(
#1380
b1000000000000110 *
b1000000000000110 /
0(
#1390
b1101 5
b1001 6
b1000 3
b110 0
b110 4
b1 C
b1000000000000110 <
1(
#1400
0(
#1410
b10 C
b1001 B
1(
#1420
0(
#1430
b11 C
1(
#1440
0(
#1450
b0 C
b1001 %
b1001 .
b1001 @
1(
#1460
b100010010 *
b100010010 /
0(
#1470
bx 5
bx 7
bx 6
b0 3
b1 2
b1 1
b10 0
b10010 4
b1 C
b100010010 <
1(
#1480
0(
#1490
b10 C
bx :
b1010 B
1(
#1500
0(
#1510
b11 C
1(
#1520
0(
#1530
b0 C
b1010 %
b1010 .
b1010 @
1(
#1540
b1010001000011 *
b1010001000011 /
0(
#1550
b1 6
b1 3
b100 2
b100 1
b11 0
b1000011 4
b1 C
b1010001000011 <
1(
#1560
0(
#1570
b10 C
b1 :
b1011 B
1(
#1580
0(
#1590
b11 C
1(
#1600
0(
#1610
b0 C
b1011 %
b1011 .
b1011 @
1(
#1620
b1001000000000101 *
b1001000000000101 /
0(
#1630
bz 5
b0 7
b1101 6
b1001 3
b0 2
b0 1
b101 0
b101 4
b1 C
b1001000000000101 <
1(
#1640
0(
#1650
b10 C
b1100 B
1(
#1660
0(
#1670
b11 C
1(
#1680
0(
#1690
b0 C
b1100 %
b1100 .
b1100 @
1(
#1700
b1000000000000110 *
b1000000000000110 /
0(
#1710
b1101 5
b1001 6
b1000 3
b110 0
b110 4
b1 C
b1000000000000110 <
1(
#1720
0(
#1730
b10 C
b1001 B
1(
#1740
0(
#1750
b11 C
1(
#1760
0(
#1770
b0 C
b1001 %
b1001 .
b1001 @
1(
#1780
b100010010 *
b100010010 /
0(
#1790
bx 5
bx 7
bx 6
b0 3
b1 2
b1 1
b10 0
b10010 4
b1 C
b100010010 <
1(
#1800
0(
#1810
b10 C
bx :
b1010 B
1(
#1820
0(
#1830
b11 C
1(
#1840
0(
#1850
b0 C
b1010 %
b1010 .
b1010 @
1(
#1860
b1010001000011 *
b1010001000011 /
0(
#1870
b1 6
b1 3
b100 2
b100 1
b11 0
b1000011 4
b1 C
b1010001000011 <
1(
#1880
0(
#1890
b10 C
b1 :
b1011 B
1(
#1900
0(
#1910
b11 C
1(
#1920
0(
#1930
b0 C
b1011 %
b1011 .
b1011 @
1(
#1940
b1001000000000101 *
b1001000000000101 /
0(
#1950
bz 5
b0 7
b1101 6
b1001 3
b0 2
b0 1
b101 0
b101 4
b1 C
b1001000000000101 <
1(
#1960
0(
#1970
b10 C
b1100 B
1(
#1980
0(
#1990
b11 C
1(
#2000
0(
#2010
b0 C
b1100 %
b1100 .
b1100 @
1(
#2020
b1000000000000110 *
b1000000000000110 /
0(
#2030
b1101 5
b1001 6
b1000 3
b110 0
b110 4
b1 C
b1000000000000110 <
1(
#2040
0(
#2050
b10 C
b1001 B
1(
#2060
0(
#2070
b11 C
1(
#2080
0(
#2090
b0 C
b1001 %
b1001 .
b1001 @
1(
#2100
b100010010 *
b100010010 /
0(
#2110
bx 5
bx 7
bx 6
b0 3
b1 2
b1 1
b10 0
b10010 4
b1 C
b100010010 <
1(
#2120
0(
#2130
b10 C
bx :
b1010 B
1(
#2140
0(
#2150
b11 C
1(
#2160
0(
#2170
b0 C
b1010 %
b1010 .
b1010 @
1(
#2180
b1010001000011 *
b1010001000011 /
0(
#2190
b1 6
b1 3
b100 2
b100 1
b11 0
b1000011 4
b1 C
b1010001000011 <
1(
#2200
0(
#2210
b10 C
b1 :
b1011 B
1(
#2220
0(
#2230
b11 C
1(
#2240
0(
#2250
b0 C
b1011 %
b1011 .
b1011 @
1(
#2260
b1001000000000101 *
b1001000000000101 /
0(
#2270
bz 5
b0 7
b1101 6
b1001 3
b0 2
b0 1
b101 0
b101 4
b1 C
b1001000000000101 <
1(
#2280
0(
#2290
b10 C
b1100 B
1(
#2300
0(
#2310
b11 C
1(
#2320
0(
#2330
b0 C
b1100 %
b1100 .
b1100 @
1(
#2340
b1000000000000110 *
b1000000000000110 /
0(
#2350
b1101 5
b1001 6
b1000 3
b110 0
b110 4
b1 C
b1000000000000110 <
1(
#2360
0(
#2370
b10 C
b1001 B
1(
#2380
0(
#2390
b11 C
1(
#2400
0(
#2410
b0 C
b1001 %
b1001 .
b1001 @
1(
#2420
b100010010 *
b100010010 /
0(
#2430
bx 5
bx 7
bx 6
b0 3
b1 2
b1 1
b10 0
b10010 4
b1 C
b100010010 <
1(
#2440
0(
#2450
b10 C
bx :
b1010 B
1(
#2460
0(
#2470
b11 C
1(
#2480
0(
#2490
b0 C
b1010 %
b1010 .
b1010 @
1(
#2500
b1010001000011 *
b1010001000011 /
0(
#2510
b1 6
b1 3
b100 2
b100 1
b11 0
b1000011 4
b1 C
b1010001000011 <
1(
#2520
0(
#2530
b10 C
b1 :
b1011 B
1(
#2540
0(
#2550
b11 C
1(
#2560
0(
#2570
b0 C
b1011 %
b1011 .
b1011 @
1(
#2580
b1001000000000101 *
b1001000000000101 /
0(
#2590
bz 5
b0 7
b1101 6
b1001 3
b0 2
b0 1
b101 0
b101 4
b1 C
b1001000000000101 <
1(
#2600
0(
#2610
b10 C
b1100 B
1(
#2620
0(
#2630
b11 C
1(
#2640
0(
#2650
b0 C
b1100 %
b1100 .
b1100 @
1(
#2660
b1000000000000110 *
b1000000000000110 /
0(
#2670
b1101 5
b1001 6
b1000 3
b110 0
b110 4
b1 C
b1000000000000110 <
1(
#2680
0(
#2690
b10 C
b1001 B
1(
#2700
0(
#2710
b11 C
1(
#2720
0(
#2730
b0 C
b1001 %
b1001 .
b1001 @
1(
#2740
b100010010 *
b100010010 /
0(
#2750
bx 5
bx 7
bx 6
b0 3
b1 2
b1 1
b10 0
b10010 4
b1 C
b100010010 <
1(
#2760
0(
#2770
b10 C
bx :
b1010 B
1(
#2780
0(
#2790
b11 C
1(
#2800
0(
#2810
b0 C
b1010 %
b1010 .
b1010 @
1(
#2820
b1010001000011 *
b1010001000011 /
0(
#2830
b1 6
b1 3
b100 2
b100 1
b11 0
b1000011 4
b1 C
b1010001000011 <
1(
#2840
0(
#2850
b10 C
b1 :
b1011 B
1(
#2860
0(
#2870
b11 C
1(
#2880
0(
#2890
b0 C
b1011 %
b1011 .
b1011 @
1(
#2900
b1001000000000101 *
b1001000000000101 /
0(
#2910
bz 5
b0 7
b1101 6
b1001 3
b0 2
b0 1
b101 0
b101 4
b1 C
b1001000000000101 <
1(
#2920
0(
#2930
b10 C
b1100 B
1(
#2940
0(
#2950
b11 C
1(
#2960
0(
#2970
b0 C
b1100 %
b1100 .
b1100 @
1(
#2980
b1000000000000110 *
b1000000000000110 /
0(
#2990
b1101 5
b1001 6
b1000 3
b110 0
b110 4
b1 C
b1000000000000110 <
1(
#3000
0(
#3010
b10 C
b1001 B
1(
#3020
0(
#3030
b11 C
1(
#3040
0(
#3050
b0 C
b1001 %
b1001 .
b1001 @
1(
#3060
b100010010 *
b100010010 /
0(
#3070
bx 5
bx 7
bx 6
b0 3
b1 2
b1 1
b10 0
b10010 4
b1 C
b100010010 <
1(
#3080
0(
#3090
b10 C
bx :
b1010 B
1(
#3100
0(
#3110
b11 C
1(
#3120
0(
#3130
b0 C
b1010 %
b1010 .
b1010 @
1(
#3140
b1010001000011 *
b1010001000011 /
0(
#3150
b1 6
b1 3
b100 2
b100 1
b11 0
b1000011 4
b1 C
b1010001000011 <
1(
#3160
0(
#3170
b10 C
b1 :
b1011 B
1(
#3180
0(
#3190
b11 C
1(
#3200
0(
#3210
b0 C
b1011 %
b1011 .
b1011 @
1(
#3220
b1001000000000101 *
b1001000000000101 /
0(
#3230
bz 5
b0 7
b1101 6
b1001 3
b0 2
b0 1
b101 0
b101 4
b1 C
b1001000000000101 <
1(
#3240
0(
#3250
b10 C
b1100 B
1(
#3260
0(
#3270
b11 C
1(
#3280
0(
#3290
b0 C
b1100 %
b1100 .
b1100 @
1(
#3300
b1000000000000110 *
b1000000000000110 /
0(
#3310
b1101 5
b1001 6
b1000 3
b110 0
b110 4
b1 C
b1000000000000110 <
1(
#3320
0(
#3330
b10 C
b1001 B
1(
#3340
0(
#3350
b11 C
1(
#3360
0(
#3370
b0 C
b1001 %
b1001 .
b1001 @
1(
#3380
b100010010 *
b100010010 /
0(
#3390
bx 5
bx 7
bx 6
b0 3
b1 2
b1 1
b10 0
b10010 4
b1 C
b100010010 <
1(
#3400
0(
#3410
b10 C
bx :
b1010 B
1(
#3420
0(
#3430
b11 C
1(
#3440
0(
#3450
b0 C
b1010 %
b1010 .
b1010 @
1(
#3460
b1010001000011 *
b1010001000011 /
0(
#3470
b1 6
b1 3
b100 2
b100 1
b11 0
b1000011 4
b1 C
b1010001000011 <
1(
#3480
0(
#3490
b10 C
b1 :
b1011 B
1(
#3500
0(
#3510
b11 C
1(
#3520
0(
#3530
b0 C
b1011 %
b1011 .
b1011 @
1(
#3540
b1001000000000101 *
b1001000000000101 /
0(
#3550
bz 5
b0 7
b1101 6
b1001 3
b0 2
b0 1
b101 0
b101 4
b1 C
b1001000000000101 <
1(
#3560
0(
#3570
b10 C
b1100 B
1(
#3580
0(
#3590
b11 C
1(
#3600
0(
#3610
b0 C
b1100 %
b1100 .
b1100 @
1(
#3620
b1000000000000110 *
b1000000000000110 /
0(
#3630
b1101 5
b1001 6
b1000 3
b110 0
b110 4
b1 C
b1000000000000110 <
1(
#3640
0(
#3650
b10 C
b1001 B
1(
#3660
0(
#3670
b11 C
1(
#3680
0(
#3690
b0 C
b1001 %
b1001 .
b1001 @
1(
#3700
b100010010 *
b100010010 /
0(
#3710
bx 5
bx 7
bx 6
b0 3
b1 2
b1 1
b10 0
b10010 4
b1 C
b100010010 <
1(
#3720
0(
#3730
b10 C
bx :
b1010 B
1(
#3740
0(
#3750
b11 C
1(
#3760
0(
#3770
b0 C
b1010 %
b1010 .
b1010 @
1(
#3780
b1010001000011 *
b1010001000011 /
0(
#3790
b1 6
b1 3
b100 2
b100 1
b11 0
b1000011 4
b1 C
b1010001000011 <
1(
#3800
0(
#3810
b10 C
b1 :
b1011 B
1(
#3820
0(
#3830
b11 C
1(
#3840
0(
#3850
b0 C
b1011 %
b1011 .
b1011 @
1(
#3860
b1001000000000101 *
b1001000000000101 /
0(
#3870
bz 5
b0 7
b1101 6
b1001 3
b0 2
b0 1
b101 0
b101 4
b1 C
b1001000000000101 <
1(
#3880
0(
#3890
b10 C
b1100 B
1(
#3900
0(
#3910
b11 C
1(
#3920
0(
#3930
b0 C
b1100 %
b1100 .
b1100 @
1(
#3940
b1000000000000110 *
b1000000000000110 /
0(
#3950
b1101 5
b1001 6
b1000 3
b110 0
b110 4
b1 C
b1000000000000110 <
1(
#3960
0(
#3970
b10 C
b1001 B
1(
#3980
0(
#3990
b11 C
1(
#4000
0(
#4010
b0 C
b1001 %
b1001 .
b1001 @
1(
#4020
b100010010 *
b100010010 /
0(
#4030
bx 5
bx 7
bx 6
b0 3
b1 2
b1 1
b10 0
b10010 4
b1 C
b100010010 <
1(
#4040
0(
#4050
b10 C
bx :
b1010 B
1(
#4060
0(
#4070
b11 C
1(
#4080
0(
#4090
b0 C
b1010 %
b1010 .
b1010 @
1(
#4100
b1010001000011 *
b1010001000011 /
0(
#4110
b1 6
b1 3
b100 2
b100 1
b11 0
b1000011 4
b1 C
b1010001000011 <
1(
#4120
0(
#4130
b10 C
b1 :
b1011 B
1(
#4140
0(
#4150
b11 C
1(
#4160
0(
#4170
b0 C
b1011 %
b1011 .
b1011 @
1(
#4180
b1001000000000101 *
b1001000000000101 /
0(
#4190
bz 5
b0 7
b1101 6
b1001 3
b0 2
b0 1
b101 0
b101 4
b1 C
b1001000000000101 <
1(
#4200
0(
#4210
b10 C
b1100 B
1(
#4220
0(
#4230
b11 C
1(
#4240
0(
#4250
b0 C
b1100 %
b1100 .
b1100 @
1(
#4260
b1000000000000110 *
b1000000000000110 /
0(
#4270
b1101 5
b1001 6
b1000 3
b110 0
b110 4
b1 C
b1000000000000110 <
1(
#4280
0(
#4290
b10 C
b1001 B
1(
#4300
0(
#4310
b11 C
1(
#4320
0(
#4330
b0 C
b1001 %
b1001 .
b1001 @
1(
#4340
b100010010 *
b100010010 /
0(
#4350
bx 5
bx 7
bx 6
b0 3
b1 2
b1 1
b10 0
b10010 4
b1 C
b100010010 <
1(
#4360
0(
#4370
b10 C
bx :
b1010 B
1(
#4380
0(
#4390
b11 C
1(
#4400
0(
#4410
b0 C
b1010 %
b1010 .
b1010 @
1(
#4420
b1010001000011 *
b1010001000011 /
0(
#4430
b1 6
b1 3
b100 2
b100 1
b11 0
b1000011 4
b1 C
b1010001000011 <
1(
#4440
0(
#4450
b10 C
b1 :
b1011 B
1(
#4460
0(
#4470
b11 C
1(
#4480
0(
#4490
b0 C
b1011 %
b1011 .
b1011 @
1(
#4500
b1001000000000101 *
b1001000000000101 /
0(
#4510
bz 5
b0 7
b1101 6
b1001 3
b0 2
b0 1
b101 0
b101 4
b1 C
b1001000000000101 <
1(
#4520
0(
#4530
b10 C
b1100 B
1(
#4540
0(
#4550
b11 C
1(
#4560
0(
#4570
b0 C
b1100 %
b1100 .
b1100 @
1(
#4580
b1000000000000110 *
b1000000000000110 /
0(
#4590
b1101 5
b1001 6
b1000 3
b110 0
b110 4
b1 C
b1000000000000110 <
1(
#4600
0(
#4610
b10 C
b1001 B
1(
#4620
0(
#4630
b11 C
1(
#4640
0(
#4650
b0 C
b1001 %
b1001 .
b1001 @
1(
#4660
b100010010 *
b100010010 /
0(
#4670
bx 5
bx 7
bx 6
b0 3
b1 2
b1 1
b10 0
b10010 4
b1 C
b100010010 <
1(
#4680
0(
#4690
b10 C
bx :
b1010 B
1(
#4700
0(
#4710
b11 C
1(
#4720
0(
#4730
b0 C
b1010 %
b1010 .
b1010 @
1(
#4740
b1010001000011 *
b1010001000011 /
0(
#4750
b1 6
b1 3
b100 2
b100 1
b11 0
b1000011 4
b1 C
b1010001000011 <
1(
#4760
0(
#4770
b10 C
b1 :
b1011 B
1(
#4780
0(
#4790
b11 C
1(
#4800
0(
#4810
b0 C
b1011 %
b1011 .
b1011 @
1(
#4820
b1001000000000101 *
b1001000000000101 /
0(
#4830
bz 5
b0 7
b1101 6
b1001 3
b0 2
b0 1
b101 0
b101 4
b1 C
b1001000000000101 <
1(
#4840
0(
#4850
b10 C
b1100 B
1(
#4860
0(
#4870
b11 C
1(
#4880
0(
#4890
b0 C
b1100 %
b1100 .
b1100 @
1(
#4900
b1000000000000110 *
b1000000000000110 /
0(
#4910
b1101 5
b1001 6
b1000 3
b110 0
b110 4
b1 C
b1000000000000110 <
1(
#4920
0(
#4930
b10 C
b1001 B
1(
#4940
0(
#4950
b11 C
1(
#4960
0(
#4970
b0 C
b1001 %
b1001 .
b1001 @
1(
#4980
b100010010 *
b100010010 /
0(
#4990
bx 5
bx 7
bx 6
b0 3
b1 2
b1 1
b10 0
b10010 4
b1 C
b100010010 <
1(
#5000
0(
#5010
b10 C
bx :
b1010 B
1(
#5020
0(
#5030
b11 C
1(
#5040
0(
#5050
b0 C
b1010 %
b1010 .
b1010 @
1(
#5060
b1010001000011 *
b1010001000011 /
0(
#5070
b1 6
b1 3
b100 2
b100 1
b11 0
b1000011 4
b1 C
b1010001000011 <
1(
#5080
0(
#5090
b10 C
b1 :
b1011 B
1(
#5100
0(
#5110
b11 C
1(
#5120
0(
#5130
b0 C
b1011 %
b1011 .
b1011 @
1(
#5140
b1001000000000101 *
b1001000000000101 /
0(
#5150
bz 5
b0 7
b1101 6
b1001 3
b0 2
b0 1
b101 0
b101 4
b1 C
b1001000000000101 <
1(
#5160
0(
#5170
b10 C
b1100 B
1(
#5180
0(
#5190
b11 C
1(
#5200
0(
#5210
b0 C
b1100 %
b1100 .
b1100 @
1(
#5220
b1000000000000110 *
b1000000000000110 /
0(
#5230
b1101 5
b1001 6
b1000 3
b110 0
b110 4
b1 C
b1000000000000110 <
1(
#5240
0(
#5250
b10 C
b1001 B
1(
#5260
0(
#5270
b11 C
1(
#5280
0(
#5290
b0 C
b1001 %
b1001 .
b1001 @
1(
#5300
b100010010 *
b100010010 /
0(
#5310
bx 5
bx 7
bx 6
b0 3
b1 2
b1 1
b10 0
b10010 4
b1 C
b100010010 <
1(
#5320
0(
#5330
b10 C
bx :
b1010 B
1(
#5340
0(
#5350
b11 C
1(
#5360
0(
#5370
b0 C
b1010 %
b1010 .
b1010 @
1(
#5380
b1010001000011 *
b1010001000011 /
0(
#5390
b1 6
b1 3
b100 2
b100 1
b11 0
b1000011 4
b1 C
b1010001000011 <
1(
#5400
0(
#5410
b10 C
b1 :
b1011 B
1(
#5420
0(
#5430
b11 C
1(
#5440
0(
#5450
b0 C
b1011 %
b1011 .
b1011 @
1(
#5460
b1001000000000101 *
b1001000000000101 /
0(
#5470
bz 5
b0 7
b1101 6
b1001 3
b0 2
b0 1
b101 0
b101 4
b1 C
b1001000000000101 <
1(
#5480
0(
#5490
b10 C
b1100 B
1(
#5500
0(
#5510
b11 C
1(
#5520
0(
#5530
b0 C
b1100 %
b1100 .
b1100 @
1(
#5540
b1000000000000110 *
b1000000000000110 /
0(
#5550
b1101 5
b1001 6
b1000 3
b110 0
b110 4
b1 C
b1000000000000110 <
1(
#5560
0(
#5570
b10 C
b1001 B
1(
#5580
0(
#5590
b11 C
1(
#5600
0(
#5610
b0 C
b1001 %
b1001 .
b1001 @
1(
#5620
b100010010 *
b100010010 /
0(
#5630
bx 5
bx 7
bx 6
b0 3
b1 2
b1 1
b10 0
b10010 4
b1 C
b100010010 <
1(
#5640
0(
#5650
b10 C
bx :
b1010 B
1(
#5660
0(
#5670
b11 C
1(
#5680
0(
#5690
b0 C
b1010 %
b1010 .
b1010 @
1(
#5700
b1010001000011 *
b1010001000011 /
0(
#5710
b1 6
b1 3
b100 2
b100 1
b11 0
b1000011 4
b1 C
b1010001000011 <
1(
#5720
0(
#5730
b10 C
b1 :
b1011 B
1(
#5740
0(
#5750
b11 C
1(
#5760
0(
#5770
b0 C
b1011 %
b1011 .
b1011 @
1(
#5780
b1001000000000101 *
b1001000000000101 /
0(
#5790
bz 5
b0 7
b1101 6
b1001 3
b0 2
b0 1
b101 0
b101 4
b1 C
b1001000000000101 <
1(
#5800
0(
#5810
b10 C
b1100 B
1(
#5820
0(
#5830
b11 C
1(
