week04/fifo.v
module fifo(Din, Dout, Wen, Ren, rst, ck, Fempty, Ffull);
  input [7:0] Din;
  output [7:0] Dout;
  input Wen, Ren, rst, ck;
  output Fempty, Ffull;

  reg [7:0] FMEM[0:15];
  reg [3:0] Wptr, Rptr;
  reg Fempty, Ffull;
  reg [7:0] obuf;
  wire [3:0] NWptr, NRptr;

  assign Dout = obuf;
  assign NWptr = Wptr + 1;
  assign NRptr = Rptr + 1;

  always @(posedge ck) begin
    if (!rst) begin
      Wptr <= 0;
      Rptr <= 0;
      Fempty <= 1;
      Ffull <= 0;
    end
    else begin
      if (Ren == 1 && Fempty != 1) begin
        obuf <= FMEM[Rptr];
        Rptr <= NRptr;
        Ffull <= 0;
        if (NRptr == Wptr) Fempty <= 1;
        else Fempty <= 0;
      end
      if (Wen == 1 && Ffull != 1) begin
        FMEM[Wptr] <= Din;
        Wptr <= NWptr;
        Fempty <= 0;
        if (NWptr == Rptr) Ffull <= 1;
        else Ffull <= 0;
      end
    end
  end
endmodule

week04/simfifo2.v
module top;
   reg[7:0] Din;
   wire [7:0] Dout;
   reg ck, rst, Wen, Ren, flag;
   wire Fempty, Ffull;

/// For test purposes
   reg [7:0] FMEM[0:15];
   reg [3:0] Wptr, Rptr;
   reg 	     Fempty0, Ffull0;
   reg [7:0] obuf;
   wire [3:0] NWptr, NRptr;
   
   assign NWptr = Wptr + 1;
   assign NRptr = Rptr + 1;
/// For test purposes

   
   fifo fifo( Din, Dout, Wen, Ren, rst, ck, Fempty, Ffull );

   initial begin
	ck = 0;
	rst = 1;
	$dumpfile( "fifo.vcd" );
	$dumpvars;
	#20 rst = 0;
	#50 rst = 1;
	#10000 
	  $display( "OK\n" );
      $finish;
   end

   always @(negedge ck)begin
     flag = $random;
     if( flag == 1 )begin
	Wen <= 1;
	Ren <= 0;
	Din = $random;
     end else begin
	Wen <= 0;
	Ren <= 1;
     end
   end

   always #10 ck <= ~ck;


   
   always @(posedge ck) begin
      if( Fempty0 != Fempty || Ffull0 != Ffull || obuf != Dout ) begin
	 $finish;
      end
   end

   always @(posedge ck) begin
      if( !rst ) begin
	 Wptr <= 0;
	 Rptr <= 0;
	 Fempty0 <= 1;
	 Ffull0 <= 0;
      end else begin
	 if( Ren == 1 && Fempty0 != 1 ) begin
	    obuf <= FMEM[Rptr];
	    Rptr <= NRptr;
	    Ffull0 <= 0;
	    if( NRptr == Wptr ) Fempty0 <= 1;
	    else Fempty0 <= 0;
	 end
	 if( Wen == 1 && Ffull0 != 1 ) begin
	    FMEM[Wptr] <= Din;
	    Wptr <= Wptr + 1;
	    Fempty0 <= 0;
	    if( NWptr == Rptr ) Ffull0 <= 1;
	    else Ffull0 <= 0;
	    
	 end
      end
   end
      
endmodule

week04/fifo.vcd
$date
	Fri May 10 11:05:30 2024
$end
$version
	Icarus Verilog
$end
$timescale
	1s
$end
$scope module top $end
$var wire 4 ! NWptr [3:0] $end
$var wire 4 " NRptr [3:0] $end
$var wire 1 # Ffull $end
$var wire 1 $ Fempty $end
$var wire 8 % Dout [7:0] $end
$var reg 8 & Din [7:0] $end
$var reg 1 ' Fempty0 $end
$var reg 1 ( Ffull0 $end
$var reg 1 ) Ren $end
$var reg 4 * Rptr [3:0] $end
$var reg 1 + Wen $end
$var reg 4 , Wptr [3:0] $end
$var reg 1 - ck $end
$var reg 1 . flag $end
$var reg 8 / obuf [7:0] $end
$var reg 1 0 rst $end
$scope module fifo $end
$var wire 8 1 Din [7:0] $end
$var wire 8 2 Dout [7:0] $end
$var wire 1 ) Ren $end
$var wire 1 + Wen $end
$var wire 1 - ck $end
$var wire 1 0 rst $end
$var wire 4 3 NWptr [3:0] $end
$var wire 4 4 NRptr [3:0] $end
$var reg 1 $ Fempty $end
$var reg 1 # Ffull $end
$var reg 4 5 Rptr [3:0] $end
$var reg 4 6 Wptr [3:0] $end
$var reg 8 7 obuf [7:0] $end
$upscope $end
$upscope $end
$enddefinitions $end
#0
$dumpvars
bx 7
bx 6
bx 5
bx 4
bx 3
bx 2
bx 1
10
bx /
x.
0-
bx ,
x+
bx *
x)
x(
x'
bx &
bx %
x$
x#
bx "
bx !
$end
#10
1-
#20
1)
0+
0.
0-
00
#30
0(
1'
b1 "
b0 *
b1 !
b0 ,
0#
1$
b1 4
b0 5
b1 3
b0 6
1-
#40
0)
1+
b1001 &
b1001 1
1.
0-
#50
1-
#60
b1101 &
b1101 1
0-
#70
0'
b10 !
b1 ,
0$
b10 3
b1 6
1-
10
#80
b1100101 &
b1100101 1
0-
#90
b11 3
b10 6
b11 !
b10 ,
1-
#100
1)
0+
0.
0-
#110
b10 "
b1 *
b1101 /
b10 4
b1 5
b1101 %
b1101 2
b1101 7
1-
#120
0)
1+
b1101 &
b1101 1
1.
0-
#130
b100 3
b11 6
b100 !
b11 ,
1-
#140
1)
0+
0.
0-
#150
b11 "
b10 *
b1100101 /
b11 4
b10 5
b1100101 %
b1100101 2
b1100101 7
1-
#160
0)
1+
b11101101 &
b11101101 1
1.
0-
#170
b101 3
b100 6
b101 !
b100 ,
1-
#180
1)
0+
0.
0-
#190
b100 "
b11 *
b1101 /
b100 4
b11 5
b1101 %
b1101 2
b1101 7
1-
#200
0)
1+
b11000110 &
b11000110 1
1.
0-
#210
b110 3
b101 6
b110 !
b101 ,
1-
#220
b10101010 &
b10101010 1
0-
#230
b111 !
b110 ,
b111 3
b110 6
1-
#240
b1110111 &
b1110111 1
0-
#250
b1000 3
b111 6
b1000 !
b111 ,
1-
#260
1)
0+
0.
0-
#270
b101 "
b100 *
b11101101 /
b101 4
b100 5
b11101101 %
b11101101 2
b11101101 7
1-
#280
0)
1+
b11110010 &
b11110010 1
1.
0-
#290
b1001 3
b1000 6
b1001 !
b1000 ,
1-
#300
1)
0+
0.
0-
#310
b110 "
b101 *
b11000110 /
b110 4
b101 5
b11000110 %
b11000110 2
b11000110 7
1-
#320
0-
#330
b111 4
b110 5
b10101010 %
b10101010 2
b10101010 7
b111 "
b110 *
b10101010 /
1-
#340
0)
1+
b1011100 &
b1011100 1
1.
0-
#350
b1010 !
b1001 ,
b1010 3
b1001 6
1-
#360
b101101 &
b101101 1
0-
#370
b1011 3
b1010 6
b1011 !
b1010 ,
1-
#380
b1100011 &
b1100011 1
0-
#390
b1100 !
b1011 ,
b1100 3
b1011 6
1-
#400
1)
0+
0.
0-
#410
b1000 4
b111 5
b1110111 %
b1110111 2
b1110111 7
b1000 "
b111 *
b1110111 /
1-
#420
0-
#430
b1001 "
b1000 *
b11110010 /
b1001 4
b1000 5
b11110010 %
b11110010 2
b11110010 7
1-
#440
0-
#450
b1010 4
b1001 5
b1011100 %
b1011100 2
b1011100 7
b1010 "
b1001 *
b1011100 /
1-
#460
0-
#470
b1011 "
b1010 *
b101101 /
b1011 4
b1010 5
b101101 %
b101101 2
b101101 7
1-
#480
0)
1+
b10010110 &
b10010110 1
1.
0-
#490
b1101 3
b1100 6
b1101 !
b1100 ,
1-
#500
b1101 &
b1101 1
0-
#510
b1110 !
b1101 ,
b1110 3
b1101 6
1-
#520
b1101011 &
b1101011 1
0-
#530
b1111 3
b1110 6
b1111 !
b1110 ,
1-
#540
b10 &
b10 1
0-
#550
b0 !
b1111 ,
b0 3
b1111 6
1-
#560
1)
0+
0.
0-
#570
b1100 4
b1011 5
b1100011 %
b1100011 2
b1100011 7
b1100 "
b1011 *
b1100011 /
1-
#580
0)
1+
b11001111 &
b11001111 1
1.
0-
#590
b1 !
b0 ,
b1 3
b0 6
1-
#600
b1010 &
b1010 1
0-
#610
b10 3
b1 6
b10 !
b1 ,
1-
#620
1)
0+
0.
0-
#630
b1101 "
b1100 *
b10010110 /
b1101 4
b1100 5
b10010110 %
b10010110 2
b10010110 7
1-
#640
0-
#650
b1110 4
b1101 5
b1101 %
b1101 2
b1101 7
b1110 "
b1101 *
b1101 /
1-
#660
0-
#670
b1111 "
b1110 *
b1101011 /
b1111 4
b1110 5
b1101011 %
b1101011 2
b1101011 7
1-
#680
0-
#690
b0 4
b1111 5
b10 %
b10 2
b10 7
b0 "
b1111 *
b10 /
1-
#700
0)
1+
b11011000 &
b11011000 1
1.
0-
#710
b11 !
b10 ,
b11 3
b10 6
1-
#720
1)
0+
0.
0-
#730
b1 4
b0 5
b11001111 %
b11001111 2
b11001111 7
b1 "
b0 *
b11001111 /
1-
#740
0)
1+
b11101011 &
b11101011 1
1.
0-
#750
b100 !
b11 ,
b100 3
b11 6
1-
#760
1)
0+
0.
0-
#770
b10 4
b1 5
b1010 %
b1010 2
b1010 7
b10 "
b1 *
b1010 /
1-
#780
0-
#790
b11 "
b10 *
b11011000 /
b11 4
b10 5
b11011000 %
b11011000 2
b11011000 7
1-
#800
0-
#810
1$
b100 4
b11 5
b11101011 %
b11101011 2
b11101011 7
1'
b100 "
b11 *
b11101011 /
1-
#820
0-
#830
1-
#840
0-
#850
1-
#860
0)
1+
b1110001 &
b1110001 1
1.
0-
#870
0'
b101 !
b100 ,
0$
b101 3
b100 6
1-
#880
b1001111 &
b1001111 1
0-
#890
b110 3
b101 6
b110 !
b101 ,
1-
#900
b111010 &
b111010 1
0-
#910
b111 !
b110 ,
b111 3
b110 6
1-
#920
1)
0+
0.
0-
#930
b101 4
b100 5
b1110001 %
b1110001 2
b1110001 7
b101 "
b100 *
b1110001 /
1-
#940
0)
1+
b11110001 &
b11110001 1
1.
0-
#950
b1000 !
b111 ,
b1000 3
b111 6
1-
#960
b1100010 &
b1100010 1
0-
#970
b1001 3
b1000 6
b1001 !
b1000 ,
1-
#980
1)
0+
0.
0-
#990
b110 "
b101 *
b1001111 /
b110 4
b101 5
b1001111 %
b1001111 2
b1001111 7
1-
#1000
0)
1+
b10001111 &
b10001111 1
1.
0-
#1010
b1010 3
b1001 6
b1010 !
b1001 ,
1-
#1020
1)
0+
0.
0-
#1030
b111 "
b110 *
b111010 /
b111 4
b110 5
b111010 %
b111010 2
b111010 7
1-
#1040
0)
1+
b10011111 &
b10011111 1
1.
0-
#1050
b1011 3
b1010 6
b1011 !
b1010 ,
1-
#1060
1)
0+
0.
0-
#1070
b1000 "
b111 *
b11110001 /
b1000 4
b111 5
b11110001 %
b11110001 2
b11110001 7
1-
#1080
0)
1+
b10001001 &
b10001001 1
1.
0-
#1090
b1100 3
b1011 6
b1100 !
b1011 ,
1-
#1100
b11010000 &
b11010000 1
0-
#1110
b1101 !
b1100 ,
b1101 3
b1100 6
1-
#1120
b1010001 &
b1010001 1
0-
#1130
b1110 3
b1101 6
b1110 !
b1101 ,
1-
#1140
1)
0+
0.
0-
#1150
b1001 "
b1000 *
b1100010 /
b1001 4
b1000 5
b1100010 %
b1100010 2
b1100010 7
1-
#1160
0-
#1170
b1010 4
b1001 5
b10001111 %
b10001111 2
b10001111 7
b1010 "
b1001 *
b10001111 /
1-
#1180
0-
#1190
b1011 "
b1010 *
b10011111 /
b1011 4
b1010 5
b10011111 %
b10011111 2
b10011111 7
1-
#1200
0-
#1210
b1100 4
b1011 5
b10001001 %
b10001001 2
b10001001 7
b1100 "
b1011 *
b10001001 /
1-
#1220
0)
1+
b111101 &
b111101 1
1.
0-
#1230
b1111 !
b1110 ,
b1111 3
b1110 6
1-
#1240
1)
0+
0.
0-
#1250
b1101 4
b1100 5
b11010000 %
b11010000 2
b11010000 7
b1101 "
b1100 *
b11010000 /
1-
#1260
0-
#1270
b1110 "
b1101 *
b1010001 /
b1110 4
b1101 5
b1010001 %
b1010001 2
b1010001 7
1-
#1280
0)
1+
b111001 &
b111001 1
1.
0-
#1290
b0 3
b1111 6
b0 !
b1111 ,
1-
#1300
b11010011 &
b11010011 1
0-
#1310
b1 !
b0 ,
b1 3
b0 6
1-
#1320
b1111000 &
b1111000 1
0-
#1330
b10 3
b1 6
b10 !
b1 ,
1-
#1340
b1001001 &
b1001001 1
0-
#1350
b11 !
b10 ,
b11 3
b10 6
1-
#1360
b101010 &
b101010 1
0-
#1370
b100 3
b11 6
b100 !
b11 ,
1-
#1380
1)
0+
0.
0-
#1390
b1111 "
b1110 *
b111101 /
b1111 4
b1110 5
b111101 %
b111101 2
b111101 7
1-
#1400
0-
#1410
b0 4
b1111 5
b111001 %
b111001 2
b111001 7
b0 "
b1111 *
b111001 /
1-
#1420
0-
#1430
b1 "
b0 *
b11010011 /
b1 4
b0 5
b11010011 %
b11010011 2
b11010011 7
1-
#1440
0-
#1450
b10 4
b1 5
b1111000 %
b1111000 2
b1111000 7
b10 "
b1 *
b1111000 /
1-
#1460
0-
#1470
b11 "
b10 *
b1001001 /
b11 4
b10 5
b1001001 %
b1001001 2
b1001001 7
1-
#1480
0-
#1490
1$
b100 4
b11 5
b101010 %
b101010 2
b101010 7
1'
b100 "
b11 *
b101010 /
1-
#1500
0)
1+
b10100011 &
b10100011 1
1.
0-
#1510
0'
b101 !
b100 ,
0$
b101 3
b100 6
1-
#1520
b10110011 &
b10110011 1
0-
#1530
b110 3
b101 6
b110 !
b101 ,
1-
#1540
b1000100 &
b1000100 1
0-
#1550
b111 !
b110 ,
b111 3
b110 6
1-
#1560
b11001011 &
b11001011 1
0-
#1570
b1000 3
b111 6
b1000 !
b111 ,
1-
#1580
1)
0+
0.
0-
#1590
b101 "
b100 *
b10100011 /
b101 4
b100 5
b10100011 %
b10100011 2
b10100011 7
1-
#1600
0-
#1610
b110 4
b101 5
b10110011 %
b10110011 2
b10110011 7
b110 "
b101 *
b10110011 /
1-
#1620
0)
1+
b11101101 &
b11101101 1
1.
0-
#1630
b1001 !
b1000 ,
b1001 3
b1000 6
1-
#1640
1)
0+
0.
0-
#1650
b111 4
b110 5
b1000100 %
b1000100 2
b1000100 7
b111 "
b110 *
b1000100 /
1-
#1660
0)
1+
b10110101 &
b10110101 1
1.
0-
#1670
b1010 !
b1001 ,
b1010 3
b1001 6
1-
#1680
b1111001 &
b1111001 1
0-
#1690
b1011 3
b1010 6
b1011 !
b1010 ,
1-
#1700
1)
0+
0.
0-
#1710
b1000 "
b111 *
b11001011 /
b1000 4
b111 5
b11001011 %
b11001011 2
b11001011 7
1-
#1720
0-
#1730
b1001 4
b1000 5
b11101101 %
b11101101 2
b11101101 7
b1001 "
b1000 *
b11101101 /
1-
#1740
0-
#1750
b1010 "
b1001 *
b10110101 /
b1010 4
b1001 5
b10110101 %
b10110101 2
b10110101 7
1-
#1760
0)
1+
b1110 &
b1110 1
1.
0-
#1770
b1100 3
b1011 6
b1100 !
b1011 ,
1-
#1780
1)
0+
0.
0-
#1790
b1011 "
b1010 *
b1111001 /
b1011 4
b1010 5
b1111001 %
b1111001 2
b1111001 7
1-
#1800
0-
#1810
1$
b1100 4
b1011 5
b1110 %
b1110 2
b1110 7
1'
b1100 "
b1011 *
b1110 /
1-
#1820
0)
1+
b11000011 &
b11000011 1
1.
0-
#1830
0'
b1101 !
b1100 ,
0$
b1101 3
b1100 6
1-
#1840
1)
0+
0.
0-
#1850
1$
b1101 4
b1100 5
b11000011 %
b11000011 2
b11000011 7
1'
b1101 "
b1100 *
b11000011 /
1-
#1860
0-
#1870
1-
#1880
0)
1+
b1010 &
b1010 1
1.
0-
#1890
0$
b1110 3
b1101 6
0'
b1110 !
b1101 ,
1-
#1900
1)
0+
0.
0-
#1910
1'
b1110 "
b1101 *
b1010 /
1$
b1110 4
b1101 5
b1010 %
b1010 2
b1010 7
1-
#1920
0-
#1930
1-
#1940
0)
1+
b10111000 &
b10111000 1
1.
0-
#1950
0'
b1111 !
b1110 ,
0$
b1111 3
b1110 6
1-
#1960
1)
0+
0.
0-
#1970
1$
b1111 4
b1110 5
b10111000 %
b10111000 2
b10111000 7
1'
b1111 "
b1110 *
b10111000 /
1-
#1980
0)
1+
b100 &
b100 1
1.
0-
#1990
0'
b0 !
b1111 ,
0$
b0 3
b1111 6
1-
#2000
b11011011 &
b11011011 1
0-
#2010
b1 3
b0 6
b1 !
b0 ,
1-
#2020
b11011001 &
b11011001 1
0-
#2030
b10 !
b1 ,
b10 3
b1 6
1-
#2040
b1110110 &
b1110110 1
0-
#2050
b11 3
b10 6
b11 !
b10 ,
1-
#2060
1)
0+
0.
0-
#2070
b0 "
b1111 *
b100 /
b0 4
b1111 5
b100 %
b100 2
b100 7
1-
#2080
0-
#2090
b1 4
b0 5
b11011011 %
b11011011 2
b11011011 7
b1 "
b0 *
b11011011 /
1-
#2100
0)
1+
b1000110 &
b1000110 1
1.
0-
#2110
b100 !
b11 ,
b100 3
b11 6
1-
#2120
1)
0+
0.
0-
#2130
b10 4
b1 5
b11011001 %
b11011001 2
b11011001 7
b10 "
b1 *
b11011001 /
1-
#2140
0)
1+
b1101001 &
b1101001 1
1.
0-
#2150
b101 !
b100 ,
b101 3
b100 6
1-
#2160
1)
0+
0.
0-
#2170
b11 4
b10 5
b1110110 %
b1110110 2
b1110110 7
b11 "
b10 *
b1110110 /
1-
#2180
0-
#2190
b100 "
b11 *
b1000110 /
b100 4
b11 5
b1000110 %
b1000110 2
b1000110 7
1-
#2200
0-
#2210
1$
b101 4
b100 5
b1101001 %
b1101001 2
b1101001 7
1'
b101 "
b100 *
b1101001 /
1-
#2220
0)
1+
b11000111 &
b11000111 1
1.
0-
#2230
0'
b110 !
b101 ,
0$
b110 3
b101 6
1-
#2240
1)
0+
0.
0-
#2250
1$
b110 4
b101 5
b11000111 %
b11000111 2
b11000111 7
1'
b110 "
b101 *
b11000111 /
1-
#2260
0-
#2270
1-
#2280
0-
#2290
1-
#2300
0)
1+
b101001 &
b101001 1
1.
0-
#2310
0'
b111 !
b110 ,
0$
b111 3
b110 6
1-
#2320
1)
0+
0.
0-
#2330
1$
b111 4
b110 5
b101001 %
b101001 2
b101001 7
1'
b111 "
b110 *
b101001 /
1-
#2340
0-
#2350
1-
#2360
0-
#2370
1-
#2380
0)
1+
b1100110 &
b1100110 1
1.
0-
#2390
0'
b1000 !
b111 ,
0$
b1000 3
b111 6
1-
#2400
1)
0+
0.
0-
#2410
1$
b1000 4
b111 5
b1100110 %
b1100110 2
b1100110 7
1'
b1000 "
b111 *
b1100110 /
1-
#2420
0)
1+
b10111010 &
b10111010 1
1.
0-
#2430
0'
b1001 !
b1000 ,
0$
b1001 3
b1000 6
1-
#2440
1)
0+
0.
0-
#2450
1$
b1001 4
b1000 5
b10111010 %
b10111010 2
b10111010 7
1'
b1001 "
b1000 *
b10111010 /
1-
#2460
0-
#2470
1-
#2480
0)
1+
b11010 &
b11010 1
1.
0-
#2490
0$
b1010 3
b1001 6
0'
b1010 !
b1001 ,
1-
#2500
b110111 &
b110111 1
0-
#2510
b1011 !
b1010 ,
b1011 3
b1010 6
1-
#2520
1)
0+
0.
0-
#2530
b1010 4
b1001 5
b11010 %
b11010 2
b11010 7
b1010 "
b1001 *
b11010 /
1-
#2540
0-
#2550
1'
b1011 "
b1010 *
b110111 /
1$
b1011 4
b1010 5
b110111 %
b110111 2
b110111 7
1-
#2560
0-
#2570
1-
#2580
0-
#2590
1-
#2600
0)
1+
b11011100 &
b11011100 1
1.
0-
#2610
0$
b1100 3
b1011 6
0'
b1100 !
b1011 ,
1-
#2620
1)
0+
0.
0-
#2630
1'
b1100 "
b1011 *
b11011100 /
1$
b1100 4
b1011 5
b11011100 %
b11011100 2
b11011100 7
1-
#2640
0-
#2650
1-
#2660
0-
#2670
1-
#2680
0)
1+
b11001111 &
b11001111 1
1.
0-
#2690
0$
b1101 3
b1100 6
0'
b1101 !
b1100 ,
1-
#2700
b11111010 &
b11111010 1
0-
#2710
b1110 !
b1101 ,
b1110 3
b1101 6
1-
#2720
b10111 &
b10111 1
0-
#2730
b1111 3
b1110 6
b1111 !
b1110 ,
1-
#2740
b10000110 &
b10000110 1
0-
#2750
b0 !
b1111 ,
b0 3
b1111 6
1-
#2760
1)
0+
0.
0-
#2770
b1101 4
b1100 5
b11001111 %
b11001111 2
b11001111 7
b1101 "
b1100 *
b11001111 /
1-
#2780
0)
1+
b110101 &
b110101 1
1.
0-
#2790
b1 !
b0 ,
b1 3
b0 6
1-
#2800
b11000001 &
b11000001 1
0-
#2810
b10 3
b1 6
b10 !
b1 ,
1-
#2820
b10011000 &
b10011000 1
0-
#2830
b11 !
b10 ,
b11 3
b10 6
1-
#2840
b1110011 &
b1110011 1
0-
#2850
b100 3
b11 6
b100 !
b11 ,
1-
#2860
1)
0+
0.
0-
#2870
b1110 "
b1101 *
b11111010 /
b1110 4
b1101 5
b11111010 %
b11111010 2
b11111010 7
1-
#2880
0-
#2890
b1111 4
b1110 5
b10111 %
b10111 2
b10111 7
b1111 "
b1110 *
b10111 /
1-
#2900
0-
#2910
b0 "
b1111 *
b10000110 /
b0 4
b1111 5
b10000110 %
b10000110 2
b10000110 7
1-
#2920
0-
#2930
b1 4
b0 5
b110101 %
b110101 2
b110101 7
b1 "
b0 *
b110101 /
1-
#2940
0)
1+
b10100001 &
b10100001 1
1.
0-
#2950
b101 !
b100 ,
b101 3
b100 6
1-
#2960
1)
0+
0.
0-
#2970
b10 4
b1 5
b11000001 %
b11000001 2
b11000001 7
b10 "
b1 *
b11000001 /
1-
#2980
0-
#2990
b11 "
b10 *
b10011000 /
b11 4
b10 5
b10011000 %
b10011000 2
b10011000 7
1-
#3000
0)
1+
b101010 &
b101010 1
1.
0-
#3010
b110 3
b101 6
b110 !
b101 ,
1-
#3020
1)
0+
0.
0-
#3030
b100 "
b11 *
b1110011 /
b100 4
b11 5
b1110011 %
b1110011 2
b1110011 7
1-
#3040
0)
1+
b10011110 &
b10011110 1
1.
0-
#3050
b111 3
b110 6
b111 !
b110 ,
1-
#3060
1)
0+
0.
0-
#3070
b101 "
b100 *
b10100001 /
b101 4
b100 5
b10100001 %
b10100001 2
b10100001 7
1-
#3080
0)
1+
b11001000 &
b11001000 1
1.
0-
#3090
b1000 3
b111 6
b1000 !
b111 ,
1-
#3100
1)
0+
0.
0-
#3110
b110 "
b101 *
b101010 /
b110 4
b101 5
b101010 %
b101010 2
b101010 7
1-
#3120
0)
1+
b1101011 &
b1101011 1
1.
0-
#3130
b1001 3
b1000 6
b1001 !
b1000 ,
1-
#3140
b10110110 &
b10110110 1
0-
#3150
b1010 !
b1001 ,
b1010 3
b1001 6
1-
#3160
1)
0+
0.
0-
#3170
b111 4
b110 5
b10011110 %
b10011110 2
b10011110 7
b111 "
b110 *
b10011110 /
1-
#3180
0-
#3190
b1000 "
b111 *
b11001000 /
b1000 4
b111 5
b11001000 %
b11001000 2
b11001000 7
1-
#3200
0)
1+
b10010010 &
b10010010 1
1.
0-
#3210
b1011 3
b1010 6
b1011 !
b1010 ,
1-
#3220
1)
0+
0.
0-
#3230
b1001 "
b1000 *
b1101011 /
b1001 4
b1000 5
b1101011 %
b1101011 2
b1101011 7
1-
#3240
0)
1+
b10000110 &
b10000110 1
1.
0-
#3250
b1100 3
b1011 6
b1100 !
b1011 ,
1-
#3260
1)
0+
0.
0-
#3270
b1010 "
b1001 *
b10110110 /
b1010 4
b1001 5
b10110110 %
b10110110 2
b10110110 7
1-
#3280
0-
#3290
b1011 4
b1010 5
b10010010 %
b10010010 2
b10010010 7
b1011 "
b1010 *
b10010010 /
1-
#3300
0-
#3310
1'
b1100 "
b1011 *
b10000110 /
1$
b1100 4
b1011 5
b10000110 %
b10000110 2
b10000110 7
1-
#3320
0)
1+
b10000100 &
b10000100 1
1.
0-
#3330
0$
b1101 3
b1100 6
0'
b1101 !
b1100 ,
1-
#3340
1)
0+
0.
0-
#3350
1'
b1101 "
b1100 *
b10000100 /
1$
b1101 4
b1100 5
b10000100 %
b10000100 2
b10000100 7
1-
#3360
0-
#3370
1-
#3380
0)
1+
b10100001 &
b10100001 1
1.
0-
#3390
0'
b1110 !
b1101 ,
0$
b1110 3
b1101 6
1-
#3400
1)
0+
0.
0-
#3410
1$
b1110 4
b1101 5
b10100001 %
b10100001 2
b10100001 7
1'
b1110 "
b1101 *
b10100001 /
1-
#3420
0)
1+
b1011 &
b1011 1
1.
0-
#3430
0'
b1111 !
b1110 ,
0$
b1111 3
b1110 6
1-
#3440
b11001001 &
b11001001 1
0-
#3450
b0 3
b1111 6
b0 !
b1111 ,
1-
#3460
1)
0+
0.
0-
#3470
b1111 "
b1110 *
b1011 /
b1111 4
b1110 5
b1011 %
b1011 2
b1011 7
1-
#3480
0)
1+
b10001111 &
b10001111 1
1.
0-
#3490
b1 3
b0 6
b1 !
b0 ,
1-
#3500
b10001000 &
b10001000 1
0-
#3510
b10 !
b1 ,
b10 3
b1 6
1-
#3520
1)
0+
0.
0-
#3530
b0 4
b1111 5
b11001001 %
b11001001 2
b11001001 7
b0 "
b1111 *
b11001001 /
1-
#3540
0)
1+
b10010010 &
b10010010 1
1.
0-
#3550
b11 !
b10 ,
b11 3
b10 6
1-
#3560
1)
0+
0.
0-
#3570
b1 4
b0 5
b10001111 %
b10001111 2
b10001111 7
b1 "
b0 *
b10001111 /
1-
#3580
0)
1+
b1001011 &
b1001011 1
1.
0-
#3590
b100 !
b11 ,
b100 3
b11 6
1-
#3600
1)
0+
0.
0-
#3610
b10 4
b1 5
b10001000 %
b10001000 2
b10001000 7
b10 "
b1 *
b10001000 /
1-
#3620
0-
#3630
b11 "
b10 *
b10010010 /
b11 4
b10 5
b10010010 %
b10010010 2
b10010010 7
1-
#3640
0)
1+
b11101100 &
b11101100 1
1.
0-
#3650
b101 3
b100 6
b101 !
b100 ,
1-
#3660
1)
0+
0.
0-
#3670
b100 "
b11 *
b1001011 /
b100 4
b11 5
b1001011 %
b1001011 2
b1001011 7
1-
#3680
0)
1+
b10000110 &
b10000110 1
1.
0-
#3690
b110 3
b101 6
b110 !
b101 ,
1-
#3700
b111011 &
b111011 1
0-
#3710
b111 !
b110 ,
b111 3
b110 6
1-
#3720
1)
0+
0.
0-
#3730
b101 4
b100 5
b11101100 %
b11101100 2
b11101100 7
b101 "
b100 *
b11101100 /
1-
#3740
0)
1+
b1010110 &
b1010110 1
1.
0-
#3750
b1000 !
b111 ,
b1000 3
b111 6
1-
#3760
b11100010 &
b11100010 1
0-
#3770
b1001 3
b1000 6
b1001 !
b1000 ,
1-
#3780
1)
0+
0.
0-
#3790
b110 "
b101 *
b10000110 /
b110 4
b101 5
b10000110 %
b10000110 2
b10000110 7
1-
#3800
0)
1+
b11011000 &
b11011000 1
1.
0-
#3810
b1010 3
b1001 6
b1010 !
b1001 ,
1-
#3820
1)
0+
0.
0-
#3830
b111 "
b110 *
b111011 /
b111 4
b110 5
b111011 %
b111011 2
b111011 7
1-
#3840
0-
#3850
b1000 4
b111 5
b1010110 %
b1010110 2
b1010110 7
b1000 "
b111 *
b1010110 /
1-
#3860
0)
1+
b11100101 &
b11100101 1
1.
0-
#3870
b1011 !
b1010 ,
b1011 3
b1010 6
1-
#3880
b101011 &
b101011 1
0-
#3890
b1100 3
b1011 6
b1100 !
b1011 ,
1-
#3900
b11001000 &
b11001000 1
0-
#3910
b1101 !
b1100 ,
b1101 3
b1100 6
1-
#3920
b10100001 &
b10100001 1
0-
#3930
b1110 3
b1101 6
b1110 !
b1101 ,
1-
#3940
b100 &
b100 1
0-
#3950
b1111 !
b1110 ,
b1111 3
b1110 6
1-
#3960
1)
0+
0.
0-
#3970
b1001 4
b1000 5
b11100010 %
b11100010 2
b11100010 7
b1001 "
b1000 *
b11100010 /
1-
#3980
0-
#3990
b1010 "
b1001 *
b11011000 /
b1010 4
b1001 5
b11011000 %
b11011000 2
b11011000 7
1-
#4000
0-
#4010
b1011 4
b1010 5
b11100101 %
b11100101 2
b11100101 7
b1011 "
b1010 *
b11100101 /
1-
#4020
0-
#4030
b1100 "
b1011 *
b101011 /
b1100 4
b1011 5
b101011 %
b101011 2
b101011 7
1-
#4040
0-
#4050
b1101 4
b1100 5
b11001000 %
b11001000 2
b11001000 7
b1101 "
b1100 *
b11001000 /
1-
#4060
0)
1+
b1010101 &
b1010101 1
1.
0-
#4070
b0 !
b1111 ,
b0 3
b1111 6
1-
#4080
b101011 &
b101011 1
0-
#4090
b1 3
b0 6
b1 !
b0 ,
1-
#4100
b10101101 &
b10101101 1
0-
#4110
b10 !
b1 ,
b10 3
b1 6
1-
#4120
b10000100 &
b10000100 1
0-
#4130
b11 3
b10 6
b11 !
b10 ,
1-
#4140
b11100111 &
b11100111 1
0-
#4150
b100 !
b11 ,
b100 3
b11 6
1-
#4160
b1001001 &
b1001001 1
0-
#4170
b101 3
b100 6
b101 !
b100 ,
1-
#4180
b11001001 &
b11001001 1
0-
#4190
b110 !
b101 ,
b110 3
b101 6
1-
#4200
b10100001 &
b10100001 1
0-
#4210
b111 3
b110 6
b111 !
b110 ,
1-
#4220
1)
0+
0.
0-
#4230
b1110 "
b1101 *
b10100001 /
b1110 4
b1101 5
b10100001 %
b10100001 2
b10100001 7
1-
#4240
0-
#4250
b1111 4
b1110 5
b100 %
b100 2
b100 7
b1111 "
b1110 *
b100 /
1-
#4260
0)
1+
b10000011 &
b10000011 1
1.
0-
#4270
b1000 !
b111 ,
b1000 3
b111 6
1-
#4280
1)
0+
0.
0-
#4290
b0 4
b1111 5
b1010101 %
b1010101 2
b1010101 7
b0 "
b1111 *
b1010101 /
1-
#4300
0-
#4310
b1 "
b0 *
b101011 /
b1 4
b0 5
b101011 %
b101011 2
b101011 7
1-
#4320
0-
#4330
b10 4
b1 5
b10101101 %
b10101101 2
b10101101 7
b10 "
b1 *
b10101101 /
1-
#4340
0-
#4350
b11 "
b10 *
b10000100 /
b11 4
b10 5
b10000100 %
b10000100 2
b10000100 7
1-
#4360
0)
1+
b10000110 &
b10000110 1
1.
0-
#4370
b1001 3
b1000 6
b1001 !
b1000 ,
1-
#4380
1)
0+
0.
0-
#4390
b100 "
b11 *
b11100111 /
b100 4
b11 5
b11100111 %
b11100111 2
b11100111 7
1-
#4400
0-
